regex_cleaner.py
regex_cleaner-1.0.2.dist-info/LICENSE
regex_cleaner-1.0.2.dist-info/METADATA
regex_cleaner-1.0.2.dist-info/WHEEL
regex_cleaner-1.0.2.dist-info/entry_points.txt
regex_cleaner-1.0.2.dist-info/top_level.txt
regex_cleaner-1.0.2.dist-info/RECORD
