Metadata-Version: 2.1
Name: regex-cleaner
Version: 1.0.2
Summary: A small package to convert verbose regex patterns to simple regex patterns.
Home-page: https://github.com/lockieRichter/regex_cleaner
Author: Lockie Richter
Author-email: richter.lockie@gmail.com
License: UNKNOWN
Platform: UNKNOWN
Classifier: Programming Language :: Python :: 3
Classifier: License :: OSI Approved :: MIT License
Classifier: Operating System :: OS Independent
Requires-Python: >=3.6
Requires-Dist: regex
